fastapi_returns/__init__.py
fastapi_returns/_routers.py
fastapi_returns-0.1.2.dist-info/WHEEL
fastapi_returns-0.1.2.dist-info/METADATA
fastapi_returns-0.1.2.dist-info/RECORD
