Metadata-Version: 2.1
Name: fastapi-returns
Version: 0.1.2
Summary: 
Home-page: https://github.com/jakub-borusewicz/fastapi-returns
License: MIT
Author: Jakub Borusewicz
Author-email: jakub.borusewicz@gmail.com
Requires-Python: >=3.7,<4.0
Classifier: License :: OSI Approved :: MIT License
Classifier: Programming Language :: Python :: 3
Classifier: Programming Language :: Python :: 3.7
Classifier: Programming Language :: Python :: 3.8
Classifier: Programming Language :: Python :: 3.9
Requires-Dist: fastapi (>=0.70.0,<0.71.0)
Requires-Dist: requests (>=2.26.0,<3.0.0)
Requires-Dist: returns (>=0.17.0,<0.18.0)
Project-URL: Repository, https://github.com/jakub-borusewicz/fastapi-returns
